panci/__init__.py
panci/ciconfig.py
panci/cli.py
panci/tox2travis.py
panci/toxconfig.py
panci/toxquickstart.py
panci/travis2tox.py
panci/travisconfig.py
panci/tests/__init__.py
panci/tests/test_ciconfig.py
panci/tests/test_travis2tox.py
panci-0.0.2.dist-info/LICENSE
panci-0.0.2.dist-info/METADATA
panci-0.0.2.dist-info/WHEEL
panci-0.0.2.dist-info/entry_points.txt
panci-0.0.2.dist-info/top_level.txt
panci-0.0.2.dist-info/RECORD
