Metadata-Version: 2.1
Name: panci
Version: 0.0.2
Summary: Convert between Travis-CI `.travis.yml` files and Tox `tox.ini` files
Home-page: https://github.com/msabramo/python-panci
Author: Marc Abramowitz
Author-email: marc@marc-abramowitz.com
License: MIT
Keywords: tox,travis,continuous integration,CI
Platform: UNKNOWN
Classifier: Programming Language :: Python :: 2
Classifier: Programming Language :: Python :: 2.6
Classifier: Programming Language :: Python :: 2.7
Classifier: Programming Language :: Python :: 3
Classifier: Programming Language :: Python :: 3.2
Classifier: Programming Language :: Python :: 3.3
Classifier: Programming Language :: Python :: 3.4
Classifier: Topic :: Software Development :: Testing
Classifier: Natural Language :: English
Classifier: Intended Audience :: Developers
Requires-Dist: PyYAML
